{
	"backtraceGraph" : 
	{
		"commands" : 
		[
			"install"
		],
		"files" : 
		[
			"ZhkeyesIMServer/CMakeLists.txt"
		],
		"nodes" : 
		[
			{
				"file" : 0
			},
			{
				"command" : 0,
				"file" : 0,
				"line" : 30,
				"parent" : 0
			}
		]
	},
	"installers" : 
	[
		{
			"backtrace" : 1,
			"component" : "Unspecified",
			"destination" : "bin",
			"paths" : 
			[
				"bin/ZhkeyesIMServer.exe"
			],
			"targetId" : "ZhkeyesIMServer::@ee1f1e3b8f3cf5c0cff7",
			"targetIndex" : 1,
			"type" : "target"
		}
	],
	"paths" : 
	{
		"build" : "ZhkeyesIMServer",
		"source" : "ZhkeyesIMServer"
	}
}
